aria/__init__.py
aria/__main__.py
aria/cli.py
aria/config.py
aria/py.typed
aria/brain/__init__.py
aria/brain/benchmark.py
aria/brain/loader.py
aria/brain/manager.py
aria/chronicle/__init__.py
aria/chronicle/index.py
aria/connection/__init__.py
aria/connection/commands.py
aria/connection/live.py
aria/core/__init__.py
aria/core/engine.py
aria/core/parser.py
aria/core/prompt.py
aria/core/response.py
aria/core/session.py
aria/core/snapshot.py
aria/flow/__init__.py
aria/flow/runner.py
aria/holomap/__init__.py
aria/holomap/diff.py
aria/holomap/stats.py
aria/holomap/validator.py
aria/server/__init__.py
aria/server/app.py
aria/server/app_v2.py
aria/simulator/__init__.py
aria/simulator/simulator.py
aria/tour/__init__.py
aria/tour/loader.py
aria/tour/runner.py
aria/tour/validator.py
aria/watch/__init__.py
aria/watch/monitor.py
aria_cli-1.0.9.dist-info/METADATA
aria_cli-1.0.9.dist-info/WHEEL
aria_cli-1.0.9.dist-info/entry_points.txt
aria_cli-1.0.9.dist-info/RECORD
