Metadata-Version: 2.4
Name: aria-cli
Version: 1.0.9
Summary: ARIA - Adaptive Runtime Intelligence Architecture. Cognitive CLI with live folder-based messaging.
Project-URL: Homepage, https://github.com/lenix-project/aria-cli
Project-URL: Documentation, https://aria.lenix.dev
Project-URL: Repository, https://github.com/lenix-project/aria-cli
Author-email: Lenix Project <aria@lenix.dev>
License-Expression: Apache-2.0
Keywords: ai,cognitive,connection,explainer,holomap,llm,messaging,runtime,self-narrating,visualization
Classifier: Development Status :: 4 - Beta
Classifier: Environment :: Console
Classifier: Intended Audience :: Developers
Classifier: License :: OSI Approved :: Apache Software License
Classifier: Operating System :: OS Independent
Classifier: Programming Language :: Python :: 3
Classifier: Programming Language :: Python :: 3.10
Classifier: Programming Language :: Python :: 3.11
Classifier: Programming Language :: Python :: 3.12
Classifier: Programming Language :: Python :: 3.13
Classifier: Topic :: Scientific/Engineering :: Artificial Intelligence
Classifier: Topic :: Software Development :: Libraries :: Python Modules
Requires-Python: >=3.10
Requires-Dist: click>=8.0
Requires-Dist: pydantic>=2.0
Requires-Dist: rich>=13.0
Provides-Extra: dev
Requires-Dist: fastapi>=0.100.0; extra == 'dev'
Requires-Dist: httpx>=0.25.0; extra == 'dev'
Requires-Dist: huggingface-hub>=0.20.0; extra == 'dev'
Requires-Dist: llama-cpp-python>=0.2.0; extra == 'dev'
Requires-Dist: mypy>=1.0; extra == 'dev'
Requires-Dist: networkx>=3.0; extra == 'dev'
Requires-Dist: plotly>=5.0; extra == 'dev'
Requires-Dist: pytest-asyncio>=0.21.0; extra == 'dev'
Requires-Dist: pytest>=7.0; extra == 'dev'
Requires-Dist: ruff>=0.1.0; extra == 'dev'
Requires-Dist: uvicorn[standard]>=0.20.0; extra == 'dev'
Requires-Dist: watchfiles>=0.20.0; extra == 'dev'
Requires-Dist: websockets>=11.0; extra == 'dev'
Provides-Extra: full
Requires-Dist: fastapi>=0.100.0; extra == 'full'
Requires-Dist: httpx>=0.25.0; extra == 'full'
Requires-Dist: huggingface-hub>=0.20.0; extra == 'full'
Requires-Dist: llama-cpp-python>=0.2.0; extra == 'full'
Requires-Dist: networkx>=3.0; extra == 'full'
Requires-Dist: plotly>=5.0; extra == 'full'
Requires-Dist: uvicorn[standard]>=0.20.0; extra == 'full'
Requires-Dist: watchfiles>=0.20.0; extra == 'full'
Requires-Dist: websockets>=11.0; extra == 'full'
Provides-Extra: llm
Requires-Dist: llama-cpp-python>=0.2.0; extra == 'llm'
Provides-Extra: server
Requires-Dist: fastapi>=0.100.0; extra == 'server'
Requires-Dist: uvicorn[standard]>=0.20.0; extra == 'server'
Requires-Dist: websockets>=11.0; extra == 'server'
Provides-Extra: viz
Requires-Dist: networkx>=3.0; extra == 'viz'
Requires-Dist: plotly>=5.0; extra == 'viz'
